{
  "id": "6a1ff0de28c69e1f4aec480b",
  "idMemberCreator": "6889d48cd74e87a6e79c7465",
  "data": {
    "board": {
      "id": "6a1d996f031816bdf557c834",
      "name": "Solutions Engineering onboarding - 2026 Bashar Al-Fallouji",
      "shortLink": "NzzPI83k"
    },
    "card": {
      "id": "6a1d996f031816bdf557c857",
      "name": "Software to install on laptop",
      "idShort": 6,
      "shortLink": "7RV6GDeR"
    },
    "checklist": {
      "id": "6a1d996f031816bdf557c909",
      "name": "Tools to install"
    },
    "checkItem": {
      "id": "6a1d996f031816bdf557ce00",
      "name": "IDE of your choice",
      "state": "complete",
      "textData": {
        "emoji": {}
      }
    }
  },
  "agenticIdentity": null,
  "appCreator": null,
  "type": "updateCheckItemStateOnCard",
  "date": "2026-06-03T09:16:14.989Z",
  "limits": null,
  "memberCreator": {
    "id": "6889d48cd74e87a6e79c7465",
    "aaId": "712020:453c6a54-25f2-4a66-8f67-d69bb70bb7af",
    "activityBlocked": false,
    "avatarHash": "546a4f5cb6c27ad9f2acde1a882d7b6d",
    "avatarUrl": "https://trello-members.s3.amazonaws.com/6889d48cd74e87a6e79c7465/546a4f5cb6c27ad9f2acde1a882d7b6d",
    "bio": "",
    "bioData": {
      "emoji": {}
    },
    "confirmed": true,
    "fullName": "Mathias Conradt",
    "idEnterprise": "5e7b85d60e998e399d7050e0",
    "idEnterprisesDeactivated": [],
    "idMemberReferrer": null,
    "idPremOrgsAdmin": [],
    "initials": "MC",
    "memberType": "normal",
    "nonPublic": {
      "fullName": "Mathias Conradt",
      "initials": "MC",
      "avatarUrl": "https://trello-members.s3.amazonaws.com/6889d48cd74e87a6e79c7465/58a66772a7667e2d43e80ee6dbf4913f",
      "avatarHash": "58a66772a7667e2d43e80ee6dbf4913f"
    },
    "nonPublicAvailable": true,
    "products": [],
    "url": "https://trello.com/u/mathiasconradt_sonar",
    "username": "mathiasconradt_sonar",
    "dateLastImpression": "2026-06-08T17:50:40.250Z",
    "status": "disconnected"
  }
}
